{
  "id": "wEfmIVLx",
  "kind": "scheme",
  "url": "https://supportgowhere.life.gov.sg/schemes/wEfmIVLx/cpf-life",
  "title": "CPF LIFE",
  "text": "CPF LIFE - SupportGoWhere\nCPF LIFE\nShare link\nCPF Lifelong Income For the Elderly (CPF LIFE) is a national longevity insurance annuity scheme that provides you with monthly payouts no matter how long you live.\nSCHEME HIGHLIGHTS\nMonthly payouts for life\nOffers various plans to suit individual preferences and needs\nOption to start payouts at a later age up to age 70, where monthly payouts will increase by up to 7% for each year of deferral\nCollapse all sections\nAbout this support\n\nProvides a lifelong monthly payout to protect against outliving one’s savings\n\nUnlike private annuity plans, which are subject to investment market returns, CPF LIFE monies are guaranteed by the government and earn a risk-free interest of up to 6% per annum\n\nOffers various plans to suit individual preferences and needs:\n\nEscalating Plan\n\n\t\n\nIncreasing monthly payouts to help you maintain your lifestyle when prices increase.\n\n\n\n\nStandard Plan\n\n\t\n\nSteady monthly payouts even if you may have to keep within a fixed budget and adjust your lifestyle when prices increase.\n\n\n\n\nBasic Plan\n\n\t\n\nPayouts that will get progressively lower when balances fall below $60,000. You may have to lower your lifestyle further when prices increase.\n\nOption to start payouts at a later age to receive up to a 7% increase in monthly payout.\n\nWho is this for?\n\nSingapore Citizen or Permanent Resident born in 1958 and after, with at least $60,000 in the Retirement Account when you start your monthly payouts, will be automatically included in CPF LIFE\n\nIf you are a Singapore Citizen or Permanent Resident who is not automatically included in CPF LIFE, you can still choose to join CPF LIFE as long as you are a Singapore Citizen or Permanent Resident, anytime from 65 to one month before you reach 80\n\nYou can choose to be exempted from CPF LIFE if you have a pension or private annuity plan that pays the same or higher monthly payouts than as CPF LIFE\n\nHow to apply?\n\nCPF Board will send you a notification three months before your 65th birthday on the options you have about your CPF savings and how you can make an informed decision using the Plan my monthly payouts service\n\nIf you have not instructed the CPF Board regarding your payouts by then, your payouts will automatically start when you turn 70 under the LIFE Standard Plan\n\nWhere can I find help?\n\nView more details\n\nCPF Hotline: 1800-227-1188\n\nTo avoid waiting on the line, you may book an appointment here.\n\nAirtime charges apply for mobile calls to 1800 service lines. Calls are free of charge only if made from regular land lines in Singapore.\n\nSubmit an enquiry\n\nVisit your nearest branch\n\nNote: By appointment only\n\nScheme last updated 10 Mar 2026\nSUPPORT RECOMMENDER\nAnswer a few questions to find schemes and services you may be eligible for.\nCheck now",
  "char_count": 2792,
  "scraped_at": "2026-05-27T14:39:34.464763+00:00",
  "topics": []
}