{
  "id": "iO9WdkX4",
  "kind": "service",
  "url": "https://supportgowhere.life.gov.sg/services/iO9WdkX4/counselling",
  "title": "Counselling",
  "text": "Counselling - SupportGoWhere\nCounselling\nShare link\nProvides counselling and psychotherapy to individuals, couples and families facing interpersonal, intrapersonal and mental health issues.\nSERVICE HIGHLIGHTS\nCentre-based, Home-based, Online\nFees payable\nReferral not required\nSERVICE PROVIDERS\nFind service providers near you\nCollapse all sections\nAbout this support\n\nCounselling and therapy services include:\n\nFamily Therapy\n\nCouple/Marital Therapy\n\nIndividual Psychotherapy\n\nPre-marital counselling and marriage preparation\n\nCounselling on sexuality and sexual issues\n\nCounselling and therapy sessions can be conducted in-person or online via Zoom.\n\n\n\n\nHelplines:\n\nCare Corner Counselling Centre also runs a toll-free Mandarin Counselling Hotline at 1800 353 5800 daily from 10am to 10pm, excluding public holidays. \n\nSAMH Insight Centre also provides a toll-free helpline at 1800 287 7019 (9am to 6pm on weekdays, except 1pm to 2pm and public holidays).\n\nWho is this for?\n\nIndividuals, couples and families with issues such as:\n\nMarital and relationship issues\n\nFamily and parenting issues\n\nGrief and loss\n\nMental health\n\nPersonal challenges\n\nStress\n\nTrauma\n\nWhat to expect?\n\nThe service provider will assess the request for counselling and ask your presenting issues and preferred day/time for the counselling and arrange a slot for you accordingly.\n\nThe staff will also provide information on the fees.\n\nCounselling intake and assessment is conducted at the first appointment and the client will see the same counsellor for the subsequent sessions until the case is closed or transferred.\n\nIf counselling is not suitable, the counsellor may refer you to other appropriate services.\n\nA counselling session takes around 1 hour.\n\nMost issues will need more than 1 counselling session to resolve.\n\nFees payable for all service providers except SAMH Insight Centre.\n\nHow to apply?\n\nFor enquiries or appointment booking, call or email the respective service provider.\n\nInformation last updated on 12 Sep 2025\nService Providers\nFind service providers near you\nFilters\nSort By\nREACH Community Service Ltd\nCentre-based\nHome-based\nOnline\n307 Shunfu Road, #01-137, 570307\nView in Map\nShow more details\nIntellect Company Pte Ltd.\nCentre-based\nHome-based\nOnline\n252 Tembeling Road, Tembeling Centre, #01-09 , 423731\nView in Map\nShow more details\nCentre for Psychotherapy Ltd\nCentre-based\nHome-based\nOnline\n7 Race Course Lane, Tai Guan Ong See Association Building, #02-01, 218734\nView in Map\nShow more details\nIncontact Counselling & Training Pte ltd\nCentre-based\nHome-based\nOnline\n7 Maxwell Road, MND Building, Annexe B, #04-04, 069111\nView in Map\nShow more details\nHope For Tomorrow Psychology Centre Private Limited\nCentre-based\nHome-based\nOnline\n19 Lorong Kilat, #01-04, 598120\nView in Map\nShow more details\nIntellect Company Pte Ltd.\nCentre-based\nHome-based\nOnline\n11 Bidadari Park Drive, The Woodleigh Mall, #02-03/05/06/07, 367803\nView in Map\nShow more details\nSingapore Counselling Centre\nCentre-based\nHome-based\nOnline\n51 Cuppage Road, #03-03, 229469\nView in Map\nShow more details\nIntellect Company Pte Ltd.\nCentre-based\nHome-based\nOnline\n11 Prinsep Link, The Foundry, 187949\nView in Map\nShow more details\nViriya Therapy Centre\nCentre-based\nHome-based\nOnline\n72 Shrewsbury Road, 307837\nView in Map\nShow more details\nViriya Mental Wellness Hub\nCentre-based\nHome-based\nOnline\n52 Kent Road, #01-16, 210052\nView in Map\nShow more details\nIntellect Company Pte Ltd.\nCentre-based\nHome-based\nOnline\n5 Straits View, East Tower Marina One, BE-60/61, 018935\nView in Map\nShow more details\nIntellect Company Pte Ltd.\nCentre-based\nHome-based\nOnline\n171 Tras Street, Union Building, #02-179, 079025\nView in Map\nShow more details\nAppleTree Counselling Pte Ltd\nCentre-based\nHome-based\nOnline\n865 Mountbatten Road, Katong Shopping Centre, #06-01, 437844\nView in Map\nShow more details\nCare Community Services Society\nCentre-based\nHome-based\nOnline\n103 Lavender Street, CarePoint, #01-02, 338725\nView in Map\nShow more details\nSAMH Insight Centre\nCentre-based\n69 Toa Payoh Lorong 4, #01-365, 310069\nView in Map\nShow more details\nCare Corner Counselling Centre\nCentre-based\nOnline\n62B Lorong 4 Toa Payoh, #02-143, 312062\nView in Map\nShow more details\nShan You Counselling & Casework\nCentre-based\n5 Upper Boon Keng Rd, #02-15, 380005\nView in Map\nShow more details\nCounselling and Care Centre\nCentre-based\nOnline\n536 Upper Cross Street, Hong Lim Complex, #05-241, 050536\nView in Map\nShow more details\nWINGS Counselling Centre\nCentre-based\nOnline\n179 Bartley Road, 539784\nView in Map\nShow more details\nEagles Mediation & Counselling Centre (EMCC)\nCentre-based\nOnline\n100 Victoria Street, National Library Building, #11-02, 188064\nView in Map\nShow more details",
  "char_count": 4736,
  "scraped_at": "2026-05-27T14:43:54.406981+00:00",
  "topics": []
}