{
  "id": "SVC-MLH",
  "kind": "service",
  "url": "https://supportgowhere.life.gov.sg/services/SVC-MLH/mindset-learning-hub",
  "title": "Mindset Learning Hub",
  "text": "Mindset Learning Hub - SupportGoWhere\nMindset Learning Hub\nShare link\nProvides vocational training, job placement and job support for persons with mental health conditions.\nSERVICE HIGHLIGHTS\nCentre-based, Online\nFree\nReferral required\nSERVICE PROVIDERS\nFind service providers near you\nCollapse all sections\nAbout this support\n\nPre-vocation intervention (Employment guidance and counselling, Service linkages and coordination)\n\nVocational Rehabilitation (Core modules include Soft and Employability skills, Work skills, Life skills)\n\nTraineeship (may include settings in Café / F&B, Cleaning, Retail, Administrative, Customer service and community outreach)\n\nJob Placement\n\nJob Support (up to 9 months post placement)\n\nPeer Support\n\nWho is this for?\n\nPersons-In-Recovery and Persons-At-Risk of developing mental health related conditions, who are seeking skills training and gainful employment opportunities.\n\nWhat to expect?\n\nFirst contact and phone call screening of a referral will be made within 3 working days.\n\nSubsequently, a physical appointment for intake will be set within 7 working days (subject to client’s availability).\n\nEnrolment results will be made known to client or Next-of-Kin on the 10th working day from referral date.\n\nHow to apply?\n\nIndividuals can call the agency to make an appointment for the intake assessment, or ask the referring source (e.g. hospital) to make a referral to SAMH.\n\nInformation last updated on 17 Sep 2025\nService Providers\nFind service providers near you\nFilters\nSort By\nSAMH MINDSET Learning Hub\nCentre-based\nOnline\n257 Jurong East Street 24, 01-405, 600257\nView in Map\nShow more details",
  "char_count": 1636,
  "scraped_at": "2026-05-27T14:42:21.651638+00:00",
  "topics": []
}